[
    {
        "id": 1,
        "name": "bulbasaur",
        "typo": [
            {
                "type": "grass"
            },
            {
                "type": "poison"
            }
        ]
    },
    {
        "id": 2,
        "name": "ivysaur",
        "typo": [
            {
                "type": "grass"
            },
            {
                "type": "poison"
            }
        ]
    },
    {
        "id": 3,
        "name": "venusaur",
        "typo": [
            {
                "type": "grass"
            },
            {
                "type": "poison"
            }
        ]
    },
    {
        "id": 4,
        "name": "charmander",
        "typo": [
            {
                "type": "fire"
            }
        ]
    },
    {
        "id": 5,
        "name": "charmeleon",
        "typo": [
            {
                "type": "fire"
            }
        ]
    },
    {
        "id": 6,
        "name": "charizard",
        "typo": [
            {
                "type": "fire"
            },
            {
                "type": "flying"
            }
        ]
    },
    {
        "id": 7,
        "name": "squirtle",
        "typo": [
            {
                "type": "water"
            }
        ]
    },
    {
        "id": 8,
        "name": "wartortle",
        "typo": [
            {
                "type": "water"
            }
        ]
    },
    {
        "id": 9,
        "name": "blastoise",
        "typo": [
            {
                "type": "water"
            }
        ]
    },
    {
        "id": 10,
        "name": "caterpie",
        "typo": [
            {
                "type": "bug"
            }
        ]
    },
    {
        "id": 11,
        "name": "metapod",
        "typo": [
            {
                "type": "bug"
            }
        ]
    },
    {
        "id": 12,
        "name": "butterfree",
        "typo": [
            {
                "type": "bug"
            },
            {
                "type": "flying"
            }
        ]
    },
    {
        "id": 13,
        "name": "weedle",
        "typo": [
            {
                "type": "bug"
            },
            {
                "type": "poison"
            }
        ]
    },
    {
        "id": 14,
        "name": "kakuna",
        "typo": [
            {
                "type": "bug"
            },
            {
                "type": "poison"
            }
        ]
    },
    {
        "id": 15,
        "name": "beedrill",
        "typo": [
            {
                "type": "bug"
            },
            {
                "type": "poison"
            }
        ]
    },
    {
        "id": 16,
        "name": "pidgey",
        "typo": [
            {
                "type": "normal"
            },
            {
                "type": "flying"
            }
        ]
    },
    {
        "id": 17,
        "name": "pidgeotto",
        "typo": [
            {
                "type": "normal"
            },
            {
                "type": "flying"
            }
        ]
    },
    {
        "id": 18,
        "name": "pidgeot",
        "typo": [
            {
                "type": "normal"
            },
            {
                "type": "flying"
            }
        ]
    },
    {
        "id": 19,
        "name": "rattata",
        "typo": [
            {
                "type": "normal"
            }
        ]
    },
    {
        "id": 20,
        "name": "raticate",
        "typo": [
            {
                "type": "normal"
            }
        ]
    },
    {
        "id": 21,
        "name": "spearow",
        "typo": [
            {
                "type": "normal"
            },
            {
                "type": "flying"
            }
        ]
    },
    {
        "id": 22,
        "name": "fearow",
        "typo": [
            {
                "type": "normal"
            },
            {
                "type": "flying"
            }
        ]
    },
    {
        "id": 23,
        "name": "ekans",
        "typo": [
            {
                "type": "poison"
            }
        ]
    },
    {
        "id": 24,
        "name": "arbok",
        "typo": [
            {
                "type": "poison"
            }
        ]
    },
    {
        "id": 25,
        "name": "pikachu",
        "typo": [
            {
                "type": "electric"
            }
        ]
    },
    {
        "id": 26,
        "name": "raichu",
        "typo": [
            {
                "type": "electric"
            }
        ]
    },
    {
        "id": 27,
        "name": "sandshrew",
        "typo": [
            {
                "type": "ground"
            }
        ]
    },
    {
        "id": 28,
        "name": "sandslash",
        "typo": [
            {
                "type": "ground"
            }
        ]
    },
    {
        "id": 29,
        "name": "nidoran-f",
        "typo": [
            {
                "type": "poison"
            }
        ]
    },
    {
        "id": 30,
        "name": "nidorina",
        "typo": [
            {
                "type": "poison"
            }
        ]
    },
    {
        "id": 31,
        "name": "nidoqueen",
        "typo": [
            {
                "type": "poison"
            },
            {
                "type": "ground"
            }
        ]
    },
    {
        "id": 32,
        "name": "nidoran-m",
        "typo": [
            {
                "type": "poison"
            }
        ]
    },
    {
        "id": 33,
        "name": "nidorino",
        "typo": [
            {
                "type": "poison"
            }
        ]
    },
    {
        "id": 34,
        "name": "nidoking",
        "typo": [
            {
                "type": "poison"
            },
            {
                "type": "ground"
            }
        ]
    },
    {
        "id": 35,
        "name": "clefairy",
        "typo": [
            {
                "type": "fairy"
            }
        ]
    },
    {
        "id": 36,
        "name": "clefable",
        "typo": [
            {
                "type": "fairy"
            }
        ]
    },
    {
        "id": 37,
        "name": "vulpix",
        "typo": [
            {
                "type": "fire"
            }
        ]
    },
    {
        "id": 38,
        "name": "ninetales",
        "typo": [
            {
                "type": "fire"
            }
        ]
    },
    {
        "id": 39,
        "name": "jigglypuff",
        "typo": [
            {
                "type": "normal"
            },
            {
                "type": "fairy"
            }
        ]
    },
    {
        "id": 40,
        "name": "wigglytuff",
        "typo": [
            {
                "type": "normal"
            },
            {
                "type": "fairy"
            }
        ]
    },
    {
        "id": 41,
        "name": "zubat",
        "typo": [
            {
                "type": "poison"
            },
            {
                "type": "flying"
            }
        ]
    },
    {
        "id": 42,
        "name": "golbat",
        "typo": [
            {
                "type": "poison"
            },
            {
                "type": "flying"
            }
        ]
    },
    {
        "id": 43,
        "name": "oddish",
        "typo": [
            {
                "type": "grass"
            },
            {
                "type": "poison"
            }
        ]
    },
    {
        "id": 44,
        "name": "gloom",
        "typo": [
            {
                "type": "grass"
            },
            {
                "type": "poison"
            }
        ]
    },
    {
        "id": 45,
        "name": "vileplume",
        "typo": [
            {
                "type": "grass"
            },
            {
                "type": "poison"
            }
        ]
    },
    {
        "id": 46,
        "name": "paras",
        "typo": [
            {
                "type": "bug"
            },
            {
                "type": "grass"
            }
        ]
    },
    {
        "id": 47,
        "name": "parasect",
        "typo": [
            {
                "type": "bug"
            },
            {
                "type": "grass"
            }
        ]
    },
    {
        "id": 48,
        "name": "venonat",
        "typo": [
            {
                "type": "bug"
            },
            {
                "type": "poison"
            }
        ]
    },
    {
        "id": 49,
        "name": "venomoth",
        "typo": [
            {
                "type": "bug"
            },
            {
                "type": "poison"
            }
        ]
    },
    {
        "id": 50,
        "name": "diglett",
        "typo": [
            {
                "type": "ground"
            }
        ]
    },
    {
        "id": 51,
        "name": "dugtrio",
        "typo": [
            {
                "type": "ground"
            }
        ]
    },
    {
        "id": 52,
        "name": "meowth",
        "typo": [
            {
                "type": "normal"
            }
        ]
    },
    {
        "id": 53,
        "name": "persian",
        "typo": [
            {
                "type": "normal"
            }
        ]
    },
    {
        "id": 54,
        "name": "psyduck",
        "typo": [
            {
                "type": "water"
            }
        ]
    },
    {
        "id": 55,
        "name": "golduck",
        "typo": [
            {
                "type": "water"
            }
        ]
    },
    {
        "id": 56,
        "name": "mankey",
        "typo": [
            {
                "type": "fighting"
            }
        ]
    },
    {
        "id": 57,
        "name": "primeape",
        "typo": [
            {
                "type": "fighting"
            }
        ]
    },
    {
        "id": 58,
        "name": "growlithe",
        "typo": [
            {
                "type": "fire"
            }
        ]
    },
    {
        "id": 59,
        "name": "arcanine",
        "typo": [
            {
                "type": "fire"
            }
        ]
    },
    {
        "id": 60,
        "name": "poliwag",
        "typo": [
            {
                "type": "water"
            }
        ]
    },
    {
        "id": 61,
        "name": "poliwhirl",
        "typo": [
            {
                "type": "water"
            }
        ]
    },
    {
        "id": 62,
        "name": "poliwrath",
        "typo": [
            {
                "type": "water"
            },
            {
                "type": "fighting"
            }
        ]
    },
    {
        "id": 63,
        "name": "abra",
        "typo": [
            {
                "type": "psychic"
            }
        ]
    },
    {
        "id": 64,
        "name": "kadabra",
        "typo": [
            {
                "type": "psychic"
            }
        ]
    },
    {
        "id": 65,
        "name": "alakazam",
        "typo": [
            {
                "type": "psychic"
            }
        ]
    },
    {
        "id": 66,
        "name": "machop",
        "typo": [
            {
                "type": "fighting"
            }
        ]
    },
    {
        "id": 67,
        "name": "machoke",
        "typo": [
            {
                "type": "fighting"
            }
        ]
    },
    {
        "id": 68,
        "name": "machamp",
        "typo": [
            {
                "type": "fighting"
            }
        ]
    },
    {
        "id": 69,
        "name": "bellsprout",
        "typo": [
            {
                "type": "grass"
            },
            {
                "type": "poison"
            }
        ]
    },
    {
        "id": 70,
        "name": "weepinbell",
        "typo": [
            {
                "type": "grass"
            },
            {
                "type": "poison"
            }
        ]
    },
    {
        "id": 71,
        "name": "victreebel",
        "typo": [
            {
                "type": "grass"
            },
            {
                "type": "poison"
            }
        ]
    },
    {
        "id": 72,
        "name": "tentacool",
        "typo": [
            {
                "type": "water"
            },
            {
                "type": "poison"
            }
        ]
    },
    {
        "id": 73,
        "name": "tentacruel",
        "typo": [
            {
                "type": "water"
            },
            {
                "type": "poison"
            }
        ]
    },
    {
        "id": 74,
        "name": "geodude",
        "typo": [
            {
                "type": "rock"
            },
            {
                "type": "ground"
            }
        ]
    },
    {
        "id": 75,
        "name": "graveler",
        "typo": [
            {
                "type": "rock"
            },
            {
                "type": "ground"
            }
        ]
    },
    {
        "id": 76,
        "name": "golem",
        "typo": [
            {
                "type": "rock"
            },
            {
                "type": "ground"
            }
        ]
    },
    {
        "id": 77,
        "name": "ponyta",
        "typo": [
            {
                "type": "fire"
            }
        ]
    },
    {
        "id": 78,
        "name": "rapidash",
        "typo": [
            {
                "type": "fire"
            }
        ]
    },
    {
        "id": 79,
        "name": "slowpoke",
        "typo": [
            {
                "type": "water"
            },
            {
                "type": "psychic"
            }
        ]
    },
    {
        "id": 80,
        "name": "slowbro",
        "typo": [
            {
                "type": "water"
            },
            {
                "type": "psychic"
            }
        ]
    },
    {
        "id": 81,
        "name": "magnemite",
        "typo": [
            {
                "type": "electric"
            },
            {
                "type": "steel"
            }
        ]
    },
    {
        "id": 82,
        "name": "magneton",
        "typo": [
            {
                "type": "electric"
            },
            {
                "type": "steel"
            }
        ]
    },
    {
        "id": 83,
        "name": "farfetchd",
        "typo": [
            {
                "type": "normal"
            },
            {
                "type": "flying"
            }
        ]
    },
    {
        "id": 84,
        "name": "doduo",
        "typo": [
            {
                "type": "normal"
            },
            {
                "type": "flying"
            }
        ]
    },
    {
        "id": 85,
        "name": "dodrio",
        "typo": [
            {
                "type": "normal"
            },
            {
                "type": "flying"
            }
        ]
    },
    {
        "id": 86,
        "name": "seel",
        "typo": [
            {
                "type": "water"
            }
        ]
    },
    {
        "id": 87,
        "name": "dewgong",
        "typo": [
            {
                "type": "water"
            },
            {
                "type": "ice"
            }
        ]
    },
    {
        "id": 88,
        "name": "grimer",
        "typo": [
            {
                "type": "poison"
            }
        ]
    },
    {
        "id": 89,
        "name": "muk",
        "typo": [
            {
                "type": "poison"
            }
        ]
    },
    {
        "id": 90,
        "name": "shellder",
        "typo": [
            {
                "type": "water"
            }
        ]
    },
    {
        "id": 91,
        "name": "cloyster",
        "typo": [
            {
                "type": "water"
            },
            {
                "type": "ice"
            }
        ]
    },
    {
        "id": 92,
        "name": "gastly",
        "typo": [
            {
                "type": "ghost"
            },
            {
                "type": "poison"
            }
        ]
    },
    {
        "id": 93,
        "name": "haunter",
        "typo": [
            {
                "type": "ghost"
            },
            {
                "type": "poison"
            }
        ]
    },
    {
        "id": 94,
        "name": "gengar",
        "typo": [
            {
                "type": "ghost"
            },
            {
                "type": "poison"
            }
        ]
    },
    {
        "id": 95,
        "name": "onix",
        "typo": [
            {
                "type": "rock"
            },
            {
                "type": "ground"
            }
        ]
    },
    {
        "id": 96,
        "name": "drowzee",
        "typo": [
            {
                "type": "psychic"
            }
        ]
    },
    {
        "id": 97,
        "name": "hypno",
        "typo": [
            {
                "type": "psychic"
            }
        ]
    },
    {
        "id": 98,
        "name": "krabby",
        "typo": [
            {
                "type": "water"
            }
        ]
    },
    {
        "id": 99,
        "name": "kingler",
        "typo": [
            {
                "type": "water"
            }
        ]
    },
    {
        "id": 100,
        "name": "voltorb",
        "typo": [
            {
                "type": "electric"
            }
        ]
    },
    {
        "id": 101,
        "name": "electrode",
        "typo": [
            {
                "type": "electric"
            }
        ]
    },
    {
        "id": 102,
        "name": "exeggcute",
        "typo": [
            {
                "type": "grass"
            },
            {
                "type": "psychic"
            }
        ]
    },
    {
        "id": 103,
        "name": "exeggutor",
        "typo": [
            {
                "type": "grass"
            },
            {
                "type": "psychic"
            }
        ]
    },
    {
        "id": 104,
        "name": "cubone",
        "typo": [
            {
                "type": "ground"
            }
        ]
    },
    {
        "id": 105,
        "name": "marowak",
        "typo": [
            {
                "type": "ground"
            }
        ]
    },
    {
        "id": 106,
        "name": "hitmonlee",
        "typo": [
            {
                "type": "fighting"
            }
        ]
    },
    {
        "id": 107,
        "name": "hitmonchan",
        "typo": [
            {
                "type": "fighting"
            }
        ]
    },
    {
        "id": 108,
        "name": "lickitung",
        "typo": [
            {
                "type": "normal"
            }
        ]
    },
    {
        "id": 109,
        "name": "koffing",
        "typo": [
            {
                "type": "poison"
            }
        ]
    },
    {
        "id": 110,
        "name": "weezing",
        "typo": [
            {
                "type": "poison"
            }
        ]
    },
    {
        "id": 111,
        "name": "rhyhorn",
        "typo": [
            {
                "type": "ground"
            },
            {
                "type": "rock"
            }
        ]
    },
    {
        "id": 112,
        "name": "rhydon",
        "typo": [
            {
                "type": "ground"
            },
            {
                "type": "rock"
            }
        ]
    },
    {
        "id": 113,
        "name": "chansey",
        "typo": [
            {
                "type": "normal"
            }
        ]
    },
    {
        "id": 114,
        "name": "tangela",
        "typo": [
            {
                "type": "grass"
            }
        ]
    },
    {
        "id": 115,
        "name": "kangaskhan",
        "typo": [
            {
                "type": "normal"
            }
        ]
    },
    {
        "id": 116,
        "name": "horsea",
        "typo": [
            {
                "type": "water"
            }
        ]
    },
    {
        "id": 117,
        "name": "seadra",
        "typo": [
            {
                "type": "water"
            }
        ]
    },
    {
        "id": 118,
        "name": "goldeen",
        "typo": [
            {
                "type": "water"
            }
        ]
    },
    {
        "id": 119,
        "name": "seaking",
        "typo": [
            {
                "type": "water"
            }
        ]
    },
    {
        "id": 120,
        "name": "staryu",
        "typo": [
            {
                "type": "water"
            }
        ]
    },
    {
        "id": 121,
        "name": "starmie",
        "typo": [
            {
                "type": "water"
            },
            {
                "type": "psychic"
            }
        ]
    },
    {
        "id": 122,
        "name": "mr-mime",
        "typo": [
            {
                "type": "psychic"
            },
            {
                "type": "fairy"
            }
        ]
    },
    {
        "id": 123,
        "name": "scyther",
        "typo": [
            {
                "type": "bug"
            },
            {
                "type": "flying"
            }
        ]
    },
    {
        "id": 124,
        "name": "jynx",
        "typo": [
            {
                "type": "ice"
            },
            {
                "type": "psychic"
            }
        ]
    },
    {
        "id": 125,
        "name": "electabuzz",
        "typo": [
            {
                "type": "electric"
            }
        ]
    },
    {
        "id": 126,
        "name": "magmar",
        "typo": [
            {
                "type": "fire"
            }
        ]
    },
    {
        "id": 127,
        "name": "pinsir",
        "typo": [
            {
                "type": "bug"
            }
        ]
    },
    {
        "id": 128,
        "name": "tauros",
        "typo": [
            {
                "type": "normal"
            }
        ]
    },
    {
        "id": 129,
        "name": "magikarp",
        "typo": [
            {
                "type": "water"
            }
        ]
    },
    {
        "id": 130,
        "name": "gyarados",
        "typo": [
            {
                "type": "water"
            },
            {
                "type": "flying"
            }
        ]
    },
    {
        "id": 131,
        "name": "lapras",
        "typo": [
            {
                "type": "water"
            },
            {
                "type": "ice"
            }
        ]
    },
    {
        "id": 132,
        "name": "ditto",
        "typo": [
            {
                "type": "normal"
            }
        ]
    },
    {
        "id": 133,
        "name": "eevee",
        "typo": [
            {
                "type": "normal"
            }
        ]
    },
    {
        "id": 134,
        "name": "vaporeon",
        "typo": [
            {
                "type": "water"
            }
        ]
    },
    {
        "id": 135,
        "name": "jolteon",
        "typo": [
            {
                "type": "electric"
            }
        ]
    },
    {
        "id": 136,
        "name": "flareon",
        "typo": [
            {
                "type": "fire"
            }
        ]
    },
    {
        "id": 137,
        "name": "porygon",
        "typo": [
            {
                "type": "normal"
            }
        ]
    },
    {
        "id": 138,
        "name": "omanyte",
        "typo": [
            {
                "type": "rock"
            },
            {
                "type": "water"
            }
        ]
    },
    {
        "id": 139,
        "name": "omastar",
        "typo": [
            {
                "type": "rock"
            },
            {
                "type": "water"
            }
        ]
    },
    {
        "id": 140,
        "name": "kabuto",
        "typo": [
            {
                "type": "rock"
            },
            {
                "type": "water"
            }
        ]
    },
    {
        "id": 141,
        "name": "kabutops",
        "typo": [
            {
                "type": "rock"
            },
            {
                "type": "water"
            }
        ]
    },
    {
        "id": 142,
        "name": "aerodactyl",
        "typo": [
            {
                "type": "rock"
            },
            {
                "type": "flying"
            }
        ]
    },
    {
        "id": 143,
        "name": "snorlax",
        "typo": [
            {
                "type": "normal"
            }
        ]
    },
    {
        "id": 144,
        "name": "articuno",
        "typo": [
            {
                "type": "ice"
            },
            {
                "type": "flying"
            }
        ]
    },
    {
        "id": 145,
        "name": "zapdos",
        "typo": [
            {
                "type": "electric"
            },
            {
                "type": "flying"
            }
        ]
    },
    {
        "id": 146,
        "name": "moltres",
        "typo": [
            {
                "type": "fire"
            },
            {
                "type": "flying"
            }
        ]
    },
    {
        "id": 147,
        "name": "dratini",
        "typo": [
            {
                "type": "dragon"
            }
        ]
    },
    {
        "id": 148,
        "name": "dragonair",
        "typo": [
            {
                "type": "dragon"
            }
        ]
    },
    {
        "id": 149,
        "name": "dragonite",
        "typo": [
            {
                "type": "dragon"
            },
            {
                "type": "flying"
            }
        ]
    },
    {
        "id": 150,
        "name": "mewtwo",
        "typo": [
            {
                "type": "psychic"
            }
        ]
    },
    {
        "id": 151,
        "name": "mew",
        "typo": [
            {
                "type": "psychic"
            }
        ]
    }
]